{
  "@context": [
    "https://www.w3.org/ns/credentials/v2",
    "https://w3id.org/security/data-integrity/v2"
  ],
  "id": "urn:uuid:alice-25",
  "type": [
    "VerifiableCredential",
    "AgeCredential"
  ],
  "issuer": "did:example:government",
  "issuanceDate": "2026-05-21T00:00:00Z",
  "credentialSubject": {
    "id": "did:example:alice",
    "commitment": "15812208763904488531944002872926888785309121033328603450941304508441776557164",
    "revealedAttributes": [
      "true"
    ]
  },
  "proof": {
    "type": "DataIntegrityProof",
    "cryptosuite": "poseidon-groth16-2026",
    "created": "2026-05-21T00:00:00Z",
    "verificationMethod": "did:example:government#poseidon-groth16-key-1",
    "proofPurpose": "assertionMethod",
    "proofValue": "65sGkv4kgvI_iyXiDMaUsH2R133BvN841UbZbhkl-YfEy9FMmLjsMvYozUau5Yobq6vlh6WTApFYCJIXkdUWEJSUPYEyTKEdsj2doQj8Go2m4GRvC38IGlclhIEQyl6HozOA208w7HG8glnwABzxyyImyAuV8xNW_C2ordNjYZA",
    "domain": "https://verifier.example"
  }
}